Metadata-Version: 1.2
Name: crn
Version: 0.1.0a1
Summary: A Python3.6+ CRN Simulator
Home-page: https://github.com/enricozb/python-crn
Author: Enrico Borba
Author-email: enricozb@gmail.com
License: MIT
Download-URL: https://github.com/enricozb/python-crn/archive/0.1.0a0.tar.gz
Keywords: crn,simulator,simulation
Platform: UNKNOWN
Classifier: Development Status :: 3 - Alpha
Classifier: Intended Audience :: Education
Classifier: Intended Audience :: Science/Research
Classifier: Topic :: Scientific/Engineering :: Bio-Informatics
Classifier: Topic :: Scientific/Engineering :: Chemistry
Classifier: Topic :: Scientific/Engineering :: Information Analysis
Classifier: License :: OSI Approved :: MIT License
Classifier: Programming Language :: Python :: 3.6
Classifier: Programming Language :: Python :: 3.7
Requires-Python: >=3.6
